leboncoin_api_wrapper/__init__.py
leboncoin_api_wrapper/leboncoin.py
leboncoin_api_wrapper/Ressources/__init__.py
leboncoin_api_wrapper/Ressources/departements.json
leboncoin_api_wrapper/Ressources/regions.json
leboncoin_api_wrapper-0.2.dist-info/METADATA
leboncoin_api_wrapper-0.2.dist-info/WHEEL
leboncoin_api_wrapper-0.2.dist-info/top_level.txt
leboncoin_api_wrapper-0.2.dist-info/RECORD
