Metadata-Version: 2.1
Name: leboncoin-api-wrapper
Version: 0.2
Summary: UNKNOWN
Home-page: https://github.com/Shinyhero36/Leboncoin-API-Wrapper
Author: Shinyhero36
License: MIT
Platform: UNKNOWN
Requires-Dist: requests (>=2.25.0)
Requires-Dist: cloudscraper (>=1.2.48)
Requires-Dist: dataclasses
